setup.py
rolemaker/__init__.py
rolemaker/createkey.py
rolemaker/crypto.py
rolemaker/daemon.py
rolemaker/iam.py
rolemaker/mime.types
rolemaker/mimetypes.py
rolemaker/model.py
rolemaker/rolemaker.wsgi
rolemaker/s3.py
rolemaker/server.py
rolemaker/utils.py
rolemaker.egg-info/PKG-INFO
rolemaker.egg-info/SOURCES.txt
rolemaker.egg-info/dependency_links.txt
rolemaker.egg-info/entry_points.txt
rolemaker.egg-info/not-zip-safe
rolemaker.egg-info/requires.txt
rolemaker.egg-info/top_level.txt
rolemaker/web/__init__.py
rolemaker/web/about.mako
rolemaker/web/create-status.mako
rolemaker/web/create.mako
rolemaker/web/favicon.ico
rolemaker/web/iam-ec2-role-demo.png
rolemaker/web/list.mako
rolemaker/web/loading.gif
rolemaker/web/login.mako
rolemaker/web/css/bootstrap-theme.css
rolemaker/web/css/bootstrap-theme.css.map
rolemaker/web/css/bootstrap-theme.min.css
rolemaker/web/css/bootstrap.css
rolemaker/web/css/bootstrap.css.map
rolemaker/web/css/bootstrap.min.css
rolemaker/web/css/local.css
rolemaker/web/fonts/glyphicons-halflings-regular.eot
rolemaker/web/fonts/glyphicons-halflings-regular.svg
rolemaker/web/fonts/glyphicons-halflings-regular.ttf
rolemaker/web/fonts/glyphicons-halflings-regular.woff
rolemaker/web/fonts/glyphicons-halflings-regular.woff2
rolemaker/web/js/bootstrap.js
rolemaker/web/js/bootstrap.min.js
rolemaker/web/js/collapse.js
rolemaker/web/js/create_role.js
rolemaker/web/js/jquery-1.11.3.min.js
rolemaker/web/js/jsonlint.js
rolemaker/web/js/load_role.js
rolemaker/web/js/npm.js
rolemaker/web/js/underscore-min.js