Metadata-Version: 1.1
Name: rolemaker
Version: 0.2.1
Summary: Allow users to create AWS IAM roles in a restricted fashion
Home-page: https://github.com/dacut/rolemaker
Author: David Cuthbert
Author-email: cuthbert@amazon.com
License: BSD
Keywords: aws,iam,role
Platform: UNKNOWN
Classifier: Development Status :: 2 - Pre-Alpha
Classifier: Intended Audience :: Developers
Classifier: License :: OSI Approved :: BSD License
Classifier: Programming Language :: Python
Classifier: Topic :: Software Development :: Libraries :: Python Modules
